odoo/addons/shopfloor_reception_packaging_dimension/README.rst
odoo/addons/shopfloor_reception_packaging_dimension/__init__.py
odoo/addons/shopfloor_reception_packaging_dimension/__manifest__.py
odoo/addons/shopfloor_reception_packaging_dimension/hooks.py
odoo/addons/shopfloor_reception_packaging_dimension/i18n/it.po
odoo/addons/shopfloor_reception_packaging_dimension/i18n/shopfloor_reception_packaging_dimension.pot
odoo/addons/shopfloor_reception_packaging_dimension/models/__init__.py
odoo/addons/shopfloor_reception_packaging_dimension/models/shopfloor_menu.py
odoo/addons/shopfloor_reception_packaging_dimension/readme/CONTRIBUTORS.rst
odoo/addons/shopfloor_reception_packaging_dimension/readme/DESCRIPTION.rst
odoo/addons/shopfloor_reception_packaging_dimension/services/__init__.py
odoo/addons/shopfloor_reception_packaging_dimension/services/reception.py
odoo/addons/shopfloor_reception_packaging_dimension/static/description/icon.png
odoo/addons/shopfloor_reception_packaging_dimension/static/description/index.html
odoo/addons/shopfloor_reception_packaging_dimension/tests/__init__.py
odoo/addons/shopfloor_reception_packaging_dimension/tests/test_set_package_dimension.py
odoo/addons/shopfloor_reception_packaging_dimension/views/shopfloor_menu.xml
odoo14_addon_shopfloor_reception_packaging_dimension-14.0.1.2.0.dist-info/METADATA
odoo14_addon_shopfloor_reception_packaging_dimension-14.0.1.2.0.dist-info/WHEEL
odoo14_addon_shopfloor_reception_packaging_dimension-14.0.1.2.0.dist-info/top_level.txt
odoo14_addon_shopfloor_reception_packaging_dimension-14.0.1.2.0.dist-info/RECORD
